CellClass/MCImage.py
CellClass/__init__.py
CellClass/detection.py
CellClass-0.0.6.dist-info/METADATA
CellClass-0.0.6.dist-info/WHEEL
CellClass-0.0.6.dist-info/top_level.txt
CellClass-0.0.6.dist-info/RECORD
