Metadata-Version: 2.1
Name: CellClass
Version: 0.0.6
Summary: CellClass
Author: Simon Gutwein
License: UNKNOWN
Keywords: python
Platform: UNKNOWN
Classifier: Programming Language :: Python :: 3
Classifier: Operating System :: Unix
Requires-Dist: absl-py (==1.0.0)
Requires-Dist: argon2-cffi (==21.3.0)
Requires-Dist: argon2-cffi-bindings (==21.2.0)
Requires-Dist: astunparse (==1.6.3)
Requires-Dist: attrs (==21.4.0)
Requires-Dist: beautifulsoup4 (==4.11.1)
Requires-Dist: bleach (==5.0.0)
Requires-Dist: cachetools (==5.2.0)
Requires-Dist: certifi (==2022.5.18.1)
Requires-Dist: cffi (==1.15.0)
Requires-Dist: charset-normalizer (==2.0.12)
Requires-Dist: commonmark (==0.9.1)
Requires-Dist: cycler (==0.11.0)
Requires-Dist: Cython (==0.29.30)
Requires-Dist: DeepCell (==0.12.0)
Requires-Dist: DeepCell-Toolbox (==0.11.2)
Requires-Dist: DeepCell-Tracking (==0.5.7)
Requires-Dist: defusedxml (==0.7.1)
Requires-Dist: docutils (==0.18.1)
Requires-Dist: fastjsonschema (==2.15.3)
Requires-Dist: flatbuffers (==2.0)
Requires-Dist: fonttools (==4.33.3)
Requires-Dist: gast (==0.5.3)
Requires-Dist: google-auth (==2.6.6)
Requires-Dist: google-auth-oauthlib (==0.4.6)
Requires-Dist: google-pasta (==0.2.0)
Requires-Dist: grpcio (==1.46.3)
Requires-Dist: h5py (==3.7.0)
Requires-Dist: idna (==3.3)
Requires-Dist: imageio (==2.19.3)
Requires-Dist: importlib-metadata (==4.11.4)
Requires-Dist: ipython-genutils (==0.2.0)
Requires-Dist: ipywidgets (==7.7.0)
Requires-Dist: Jinja2 (==3.1.2)
Requires-Dist: joblib (==1.1.0)
Requires-Dist: jsonschema (==4.5.1)
Requires-Dist: jupyter (==1.0.0)
Requires-Dist: jupyter-console (==6.4.3)
Requires-Dist: jupyterlab-pygments (==0.2.2)
Requires-Dist: jupyterlab-widgets (==1.1.0)
Requires-Dist: keras (==2.8.0)
Requires-Dist: Keras-Preprocessing (==1.1.2)
Requires-Dist: keyring (==23.5.1)
Requires-Dist: kiwisolver (==1.4.2)
Requires-Dist: libclang (==14.0.1)
Requires-Dist: lxml (==4.8.0)
Requires-Dist: Markdown (==3.3.7)
Requires-Dist: MarkupSafe (==2.1.1)
Requires-Dist: matplotlib (==3.5.2)
Requires-Dist: mistune (==0.8.4)
Requires-Dist: mpmath (==1.2.1)
Requires-Dist: nbclient (==0.6.3)
Requires-Dist: nbconvert (==6.5.0)
Requires-Dist: nbformat (==5.4.0)
Requires-Dist: networkx (==2.8.2)
Requires-Dist: nose (==1.3.7)
Requires-Dist: notebook (==6.4.11)
Requires-Dist: numpy (==1.19.5)
Requires-Dist: oauthlib (==3.2.0)
Requires-Dist: opencv-python (==4.5.5.64)
Requires-Dist: opencv-python-headless (==4.5.5.64)
Requires-Dist: opt-einsum (==3.3.0)
Requires-Dist: packaging (==21.3)
Requires-Dist: pandas (==1.4.2)
Requires-Dist: pandocfilters (==1.5.0)
Requires-Dist: Pillow (==9.1.1)
Requires-Dist: pkginfo (==1.8.2)
Requires-Dist: prometheus-client (==0.14.1)
Requires-Dist: protobuf (==3.19.4)
Requires-Dist: pyasn1 (==0.4.8)
Requires-Dist: pyasn1-modules (==0.2.8)
Requires-Dist: pycparser (==2.21)
Requires-Dist: pydot (==1.4.2)
Requires-Dist: Pygments (==2.12.0)
Requires-Dist: pyparsing (==3.0.9)
Requires-Dist: pyrsistent (==0.18.1)
Requires-Dist: pytz (==2022.1)
Requires-Dist: PyWavelets (==1.3.0)
Requires-Dist: qtconsole (==5.3.0)
Requires-Dist: QtPy (==2.1.0)
Requires-Dist: readme-renderer (==35.0)
Requires-Dist: requests (==2.27.1)
Requires-Dist: requests-oauthlib (==1.3.1)
Requires-Dist: requests-toolbelt (==0.9.1)
Requires-Dist: rfc3986 (==2.0.0)
Requires-Dist: rich (==12.4.4)
Requires-Dist: rsa (==4.8)
Requires-Dist: scikit-image (==0.19.2)
Requires-Dist: scikit-learn (==1.1.1)
Requires-Dist: scipy (==1.8.1)
Requires-Dist: Send2Trash (==1.8.0)
Requires-Dist: six (==1.15.0)
Requires-Dist: soupsieve (==2.3.2.post1)
Requires-Dist: spektral (==1.0.6)
Requires-Dist: tensorboard (==2.8.0)
Requires-Dist: tensorboard-data-server (==0.6.1)
Requires-Dist: tensorboard-plugin-wit (==1.8.1)
Requires-Dist: tensorflow (==2.8.2)
Requires-Dist: tensorflow-addons (==0.16.1)
Requires-Dist: tensorflow-estimator (==2.8.0)
Requires-Dist: tensorflow-io-gcs-filesystem (==0.26.0)
Requires-Dist: termcolor (==1.1.0)
Requires-Dist: terminado (==0.15.0)
Requires-Dist: threadpoolctl (==3.1.0)
Requires-Dist: tifffile (==2022.5.4)
Requires-Dist: tinycss2 (==1.1.1)
Requires-Dist: tqdm (==4.64.0)
Requires-Dist: twine (==4.0.0)
Requires-Dist: typeguard (==2.13.3)
Requires-Dist: typing-extensions (==4.2.0)
Requires-Dist: urllib3 (==1.26.9)
Requires-Dist: webencodings (==0.5.1)
Requires-Dist: Werkzeug (==2.1.2)
Requires-Dist: widgetsnbextension (==3.6.0)
Requires-Dist: wrapt (==1.14.1)
Requires-Dist: zipp (==3.8.0)
